alibabacloud_dplus20201216/__init__.py
alibabacloud_dplus20201216/client.py
alibabacloud_dplus20201216/models.py
alibabacloud_dplus20201216-1.0.8.dist-info/LICENSE
alibabacloud_dplus20201216-1.0.8.dist-info/METADATA
alibabacloud_dplus20201216-1.0.8.dist-info/WHEEL
alibabacloud_dplus20201216-1.0.8.dist-info/top_level.txt
alibabacloud_dplus20201216-1.0.8.dist-info/RECORD
